odoo/addons/account_invoice_google_document_ai/README.rst
odoo/addons/account_invoice_google_document_ai/__init__.py
odoo/addons/account_invoice_google_document_ai/__manifest__.py
odoo/addons/account_invoice_google_document_ai/i18n/account_invoice_google_document_ai.pot
odoo/addons/account_invoice_google_document_ai/i18n/it.po
odoo/addons/account_invoice_google_document_ai/models/__init__.py
odoo/addons/account_invoice_google_document_ai/models/account_move.py
odoo/addons/account_invoice_google_document_ai/models/account_move_google_document_ai.py
odoo/addons/account_invoice_google_document_ai/models/res_company.py
odoo/addons/account_invoice_google_document_ai/models/res_config_settings.py
odoo/addons/account_invoice_google_document_ai/readme/CONFIGURE.rst
odoo/addons/account_invoice_google_document_ai/readme/CONTRIBUTORS.rst
odoo/addons/account_invoice_google_document_ai/readme/DESCRIPTION.rst
odoo/addons/account_invoice_google_document_ai/static/description/icon.png
odoo/addons/account_invoice_google_document_ai/static/description/index.html
odoo/addons/account_invoice_google_document_ai/tests/__init__.py
odoo/addons/account_invoice_google_document_ai/tests/result.json
odoo/addons/account_invoice_google_document_ai/tests/test_google_document_ai.py
odoo/addons/account_invoice_google_document_ai/views/account_move.xml
odoo/addons/account_invoice_google_document_ai/views/res_config_settings.xml
odoo_addon_account_invoice_google_document_ai-16.0.1.0.0.3.dist-info/METADATA
odoo_addon_account_invoice_google_document_ai-16.0.1.0.0.3.dist-info/WHEEL
odoo_addon_account_invoice_google_document_ai-16.0.1.0.0.3.dist-info/top_level.txt
odoo_addon_account_invoice_google_document_ai-16.0.1.0.0.3.dist-info/RECORD
