Metadata-Version: 2.1
Name: odoo-addon-account_invoice_google_document_ai
Version: 16.0.1.0.0.3
Summary: Allows to import data from document using Google Document AI
Home-page: https://github.com/OCA/account-invoicing
Author: CreuBlanca,ForgeFlow,Odoo Community Association (OCA)
Author-email: support@odoo-community.org
License: AGPL-3
Classifier: Programming Language :: Python
Classifier: Framework :: Odoo
Classifier: Framework :: Odoo :: 16.0
Classifier: License :: OSI Approved :: GNU Affero General Public License v3
Requires-Python: >=3.10
Requires-Dist: google-cloud-documentai
Requires-Dist: odoo<16.1dev,>=16.0a
